pane/__init__.py
pane/dom.py
pane/expr.py
pane/mesh.py
pane/pane.cp310-win_amd64.pyd
pane-0.1.3.data/data/README/README.md
pane-0.1.3.data/data/licenses/APACHE2
pane-0.1.3.data/data/licenses/MIT
pane-0.1.3.dist-info/LICENSE
pane-0.1.3.dist-info/METADATA
pane-0.1.3.dist-info/WHEEL
pane-0.1.3.dist-info/top_level.txt
pane-0.1.3.dist-info/RECORD
